[1,["ecpdLyjvZBwrvm+cedCcQy","58HiYZ7FZHg7WvKVQBR/cd","b4IyFycz5Oi7zID6gd+cyy"],["node","root","itemNode","data","_spriteFrame","_textureSetter"],[["cc.Node",["_name","_active","_components","_prefab","_children","_parent","_contentSize"],1,9,4,2,1,5],["cc.PrefabInfo",["fileId","root","asset"],2,1,1],"cc.SpriteFrame",["cc.Prefab",["_name"],2],["17f63V3YZhOkr/zTW/owNC5",["node","itemNode"],3,1,1],["cc.Sprite",["node","_materials","_spriteFrame"],3,1,3,6]],[[3,0,2],[0,0,4,2,3,2],[0,0,1,5,2,3,6,3],[4,0,1,1],[1,1,2,1],[1,0,1,2,2],[5,0,1,2,1]],[[[[0,"ItemFly"],[1,"ItemFly",[-4],[[3,-3,-2]],[4,-1,0]],[2,"icon",false,1,[[6,-5,[0],1]],[5,"cegzjRTstCh5aWJ7Xef64V",1,0],[5,101,100]]],0,[0,1,1,0,2,2,0,0,1,0,-1,2,0,0,2,0,3,1,5],[0,0],[-1,4],[0,1]],[[{"name":"item_30021","rect":[26,24,81,81],"offset":[1.5,0.5],"originalSize":[130,130],"capInsets":[0,0,0,0]}],[2],0,[0],[5],[2]]]]