[1,0,0,[["cc.JsonAsset",["_name","json"],1]],[[0,0,1,3]],[[0,"mst_role",{"1":{"type":1,"index":21,"unlockBuildingId":124,"unlockItemId":-1,"isUnlockShow":false,"routeIds":[1,2,3,4],"skinIds":[10]},"2":{"type":1,"index":23,"unlockBuildingId":104,"unlockItemId":-1,"isUnlockShow":true,"routeIds":[101,102,103,104],"skinIds":[20]},"3":{"type":1,"index":22,"unlockBuildingId":21,"unlockItemId":-1,"isUnlockShow":true,"routeIds":[201,202],"skinIds":[30]},"4":{"type":1,"index":31,"unlockBuildingId":222,"unlockItemId":-1,"isUnlockShow":true,"routeIds":[301,302,303,304],"skinIds":[40]},"5":{"type":1,"index":32,"unlockBuildingId":210,"unlockItemId":-1,"isUnlockShow":true,"routeIds":[401,402,403,404],"skinIds":[50]},"6":{"type":1,"index":41,"unlockBuildingId":-1,"unlockItemId":206,"isUnlockShow":true,"routeIds":[501,502,503,504],"skinIds":[60]},"7":{"type":1,"index":42,"unlockBuildingId":312,"unlockItemId":-1,"isUnlockShow":true,"routeIds":[601,602,603,604],"skinIds":[70]},"8":{"type":1,"index":43,"unlockBuildingId":303,"unlockItemId":-1,"isUnlockShow":true,"routeIds":[701,702,703,704],"skinIds":[80]},"9":{"type":1,"index":53,"unlockBuildingId":405,"unlockItemId":-1,"isUnlockShow":true,"routeIds":[801],"skinIds":[90]},"10":{"type":1,"index":51,"unlockBuildingId":417,"unlockItemId":-1,"isUnlockShow":true,"routeIds":[901],"skinIds":[100]},"11":{"type":1,"index":52,"unlockBuildingId":407,"unlockItemId":-1,"isUnlockShow":true,"routeIds":[1001],"skinIds":[110]},"12":{"type":1,"index":14,"unlockBuildingId":15,"unlockItemId":-1,"isUnlockShow":true,"routeIds":[1101],"skinIds":[120]},"13":{"type":1,"index":13,"unlockBuildingId":10,"unlockItemId":-1,"isUnlockShow":true,"routeIds":[1201,1202],"skinIds":[130]},"14":{"type":1,"index":33,"unlockBuildingId":203,"unlockItemId":-1,"isUnlockShow":true,"routeIds":[1301,1302,1303],"skinIds":[140]},"15":{"type":1,"index":99,"unlockBuildingId":4444,"unlockItemId":4444,"isUnlockShow":true,"routeIds":[1401,1402,1403],"skinIds":[150]},"16":{"type":1,"index":61,"unlockBuildingId":529,"unlockItemId":-1,"isUnlockShow":true,"routeIds":[1501,1502,1503,1504],"skinIds":[160]},"17":{"type":1,"index":62,"unlockBuildingId":515,"unlockItemId":-1,"isUnlockShow":true,"routeIds":[1601,1602,1603],"skinIds":[170]},"18":{"type":1,"index":63,"unlockBuildingId":506,"unlockItemId":-1,"isUnlockShow":true,"routeIds":[1701,1702,1703],"skinIds":[180]},"19":{"type":1,"index":71,"unlockBuildingId":610,"unlockItemId":-1,"isUnlockShow":true,"routeIds":[1801,1802,1803],"skinIds":[190]},"20":{"type":1,"index":72,"unlockBuildingId":606,"unlockItemId":-1,"isUnlockShow":true,"routeIds":[1901,1902,1903],"skinIds":[200]},"21":{"type":1,"index":82,"unlockBuildingId":703,"unlockItemId":-1,"isUnlockShow":true,"routeIds":[2001,2002,2003],"skinIds":[210]},"22":{"type":1,"index":83,"unlockBuildingId":711,"unlockItemId":-1,"isUnlockShow":true,"routeIds":[2101,2102,2103],"skinIds":[220]},"23":{"type":1,"index":81,"unlockBuildingId":709,"unlockItemId":-1,"isUnlockShow":true,"routeIds":[2201,2202,2203],"skinIds":[230]},"999":{"type":11,"index":1,"unlockBuildingId":25,"unlockItemId":-1,"isUnlockShow":false,"routeIds":[],"skinIds":[9990,9991,9992]}}]],0,0,[],[],[]]