[1,0,0,[["cc.JsonAsset",["_name","json"],1]],[[0,0,1,3]],[[0,"362",{"stageId":362,"goals":"Bubbles","bubbleNums":20,"starScore":[3000,16000,28000],"bubbleIds":["3","2"],"randomIds":["3","2"],"list":[["113","112","113","2131","213","213","212y","212y","112","113","112"],["112","0","212","0","0","213y","213y","213y","0","113","0"],["17","0","0","212","0","0","213y","212y","0","212","0"],["213","0","0","213","0","0","213","0","212","0","0"],["0","213","0","0","113","0","0","2121","0","113","0"],["0","1l","0","112y","112y","0","0","213","0","1l","0"],["0","2131","0","212y","213y","213y","0","113","0","212","0"],["112","0","212y","213y","213y","0","113","0","213","0","0"],["17","0","0","212y","212y","0","0","213","0","2121","0"],["213","0","0","212","0","0","0","1l","0","17","0"],["0","213","0","0","112","0","0","212","0","212","0"],["0","1l","0","0","1l","0","113","0","213y","212y","0"],["0","2131","0","0","213","0","213","0","212y","212y","212y"],["213","0","0","112","0","212y","213y","0","213y","213y","0"],["17","0","0","1121","0","213y","212y","212y","0","113","0"],["213","0","213","0","213y","212y","213y","0","0","2131","0"],["0","212","0","213","0","213y","213y","0","0","213","0"],["0","1l","0","213","0","213","0","0","113","0","0"],["0","213","0","0","213","0","213","0","0","212","0"],["213y","213y","0","0","2131","0","113","0","0","1l","0"],["212y","213y","212y","0","0","1l","0","213","0","212","0"],["213y","213y","0","0","212","0","212","0","213y","212y","0"],["0","212","0","0","112","0","212","0","213y","213y","213y"],["0","1l","0","113y","0","0","113","0","213y","213y","0"],["0","213","0","112y","112y","0","0","1l","0","113","0"],["213","0","112y","112y","212y","0","1121","0","212","0","0"],["17","0","113y","113y","113y","0","212","0","212y","213y","0"],["213","0","113y","113y","0","213","0","213y","212y","212y","0"],["0","213","0","213","0","213","0","0","213y","213y","0"],["0","1l","0","212","0","213","0","0","212","0","0"],["0","213","0","213","0","113y","112y","0","0","113","0"],["213","0","213","0","112y","112y","113y","0","0","17","0"],["17","0","213","0","0","112y","112y","113y","0","213","0"],["2131","0","212","0","0","113y","113y","0","113","0","0"],["0","213","0","1131","0","0","213","0","213","0","0"],["0","1l","0","212","0","212","0","0","2121","0","0"],["0","212","0","213y","212y","0","212","0","0","212","0"],["212","0","113y","112y","113y","0","112","0","0","1l","0"],["17","0","113y","112y","113y","0","0","1l","0","113","0"],["212","0","112y","113y","0","0","213","0","213","0","0"],["0","213","0","213","0","0","212","0","213","0","0"],["0","1l","0","113","0","112","0","0","212","0","0"],["0","212","0","212","0","212y","213y","0","0","213","0"],["213","0","213","0","213y","213y","213y","0","0","17","0"],["17","0","112","0","0","212y","213y","0","212y","213y","0"],["0","0","0","0","0","0","0","213y","213y","212y","0"],["0","0","0","0","0","0","0","0","213y","213y","0"]]}]],0,0,[],[],[]]