[1,0,0,[["cc.JsonAsset",["_name","json"],1]],[[0,0,1,3]],[[0,"295",{"stageId":295,"goals":"Crystals","bubbleNums":8,"starScore":[2000,15000,20000],"bubbleIds":["8","7"],"randomIds":["7","8"],"list":[["0","1173","218y","117","118","217","1181","117","218y","1173","0"],["217y","1a","218y","117","218y","218y","217","217y","1a","217y","0"],["0","218y","217y","117","217y","1a","218y","217","218y","217y","0"],["2171","1z(a)1","217","217","218y","217y","218","217","1z(a)2","118","0"],["0","117y","118y","117","117","217","217","217","217y","218y","0"],["2173","1a","217y","0","218y","218y","0","217y","1a","2173","0"],["0","218y","217y","0","0","1z(a)2","0","0","218y","217y","0"],["117","1z(a)2","217","0","218y","218y","0","2171","1z(a)1","117","0"],["0","217y","217y","0","0","1a","0","0","218y","217y","0"],["217y","1a","1173","2171","218y","217y","118","2173","1a","217y","0"],["0","118y","117y","0","0","1z(a)1","0","0","217y","217y","0"],["217","1z(a)1","218","0","218y","218y","0","217","1z(a)2","117","0"],["0","118y","117y","0","0","1a","0","0","217y","118y","0"],["217y","1a","2183","2171","217y","217y","218","2183","1a","218y","0"],["0","218y","218y","0","0","1z(a)1","0","0","117y","217y","0"],["117","1z(a)1","218","0","217y","218y","0","118","1z(a)2","117","0"],["0","218y","218y","0","0","1a","0","0","118y","117y","0"],["2173","1a","217y","218","217y","218y","217","217y","1a","2173","0"],["0","218y","217y","0","0","1z(a)2","0","0","217y","218y","0"],["217","1z(a)2","118","0","217y","218y","0","118","1z(a)1","118","0"],["0","118y","117y","0","0","1a","0","0","117y","117y","0"],["218y","1a","1183","117","218y","217y","1181","2183","1a","217y","0"],["0","218y","218y","0","0","1z(a)1","0","0","217y","217y","0"],["2181","1z(a)1","118","0","217y","218y","0","118","1z(a)2","118","0"],["0","217y","218y","0","0","1a","0","0","218y","218y","0"],["2183","1a","218y","118","218y","217y","117","218y","1a","2173","0"],["0","218y","217y","0","0","1z(a)2","0","0","218y","217y","0"],["217","117","117","0","218y","217y","0","117","117","117","0"],["0","118","118","0","217y","1a","217y","0","117","118","0"],["0","0","0","0","217y","218y","0","0","0","0","0"],["0","0","0","0","0","0","0","0","0","0","0"]]}]],0,0,[],[],[]]