[1,["18ab1f24c"],["_textureSetter"],["cc.SpriteFrame"],0,[[[{"name":"btn_1","rect":[759,192,140,110],"offset":[0,0],"originalSize":[140,110],"capInsets":[0,0,0,0]}],[0],0,[0],[0],[0]],[[{"name":"btn_2","rect":[759,308,140,110],"offset":[0,0],"originalSize":[140,110],"capInsets":[0,0,0,0]}],[0],0,[0],[0],[0]],[[{"name":"btn_6","rect":[759,424,140,110],"offset":[0,0],"originalSize":[140,110],"capInsets":[0,0,0,0]}],[0],0,[0],[0],[0]],[[{"name":"floor_4","rect":[3,1644,97,94],"offset":[0,0],"originalSize":[97,94],"rotated":1,"capInsets":[49,48,48,46]}],[0],0,[0],[0],[0]],[[{"name":"btn_chehui","rect":[691,1585,46,51],"offset":[0,0],"originalSize":[46,51],"capInsets":[0,0,0,0]}],[0],0,[0],[0],[0]]]]